dpcms/version.py
django_plotly_cms-0.0.2.dist-info/METADATA
django_plotly_cms-0.0.2.dist-info/WHEEL
django_plotly_cms-0.0.2.dist-info/top_level.txt
django_plotly_cms-0.0.2.dist-info/RECORD
